setup.py
json_to_model/__init__.py
json_to_model/console.py
json_to_model/parser.py
json_to_model.egg-info/PKG-INFO
json_to_model.egg-info/SOURCES.txt
json_to_model.egg-info/dependency_links.txt
json_to_model.egg-info/entry_points.txt
json_to_model.egg-info/requires.txt
json_to_model.egg-info/top_level.txt
json_to_model/generators/__init__.py
json_to_model/generators/objc.py
json_to_model/generators/swift.py
json_to_model/generators/templates/header.h
json_to_model/generators/templates/source.m
json_to_model/generators/templates/swift.swift