Metadata-Version: 1.1
Name: json-to-model
Version: 1.1
Summary: automatically convert json to model defination
Home-page: https://github.com/clowwindy/json_to_model
Author: clowwindy
Author-email: clowwindy42@gmail.com
License: MIT
Platform: UNKNOWN
Classifier: License :: OSI Approved :: MIT License
Classifier: Programming Language :: Python :: 2
Classifier: Programming Language :: Python :: 2.6
Classifier: Programming Language :: Python :: 2.7
